fabric_cm/__init__.py
fabric_cm/credmgr/__init__.py
fabric_cm/credmgr/credmgr_proxy.py
fabric_cm/credmgr/session_helper.py
fabric_cm/credmgr/swagger_client/__init__.py
fabric_cm/credmgr/swagger_client/api_client.py
fabric_cm/credmgr/swagger_client/configuration.py
fabric_cm/credmgr/swagger_client/rest.py
fabric_cm/credmgr/swagger_client/api/__init__.py
fabric_cm/credmgr/swagger_client/api/default_api.py
fabric_cm/credmgr/swagger_client/api/tokens_api.py
fabric_cm/credmgr/swagger_client/api/version_api.py
fabric_cm/credmgr/swagger_client/models/__init__.py
fabric_cm/credmgr/swagger_client/models/decoded_token.py
fabric_cm/credmgr/swagger_client/models/jwks.py
fabric_cm/credmgr/swagger_client/models/jwks_keys.py
fabric_cm/credmgr/swagger_client/models/request.py
fabric_cm/credmgr/swagger_client/models/revoke_list.py
fabric_cm/credmgr/swagger_client/models/status200_ok_no_content.py
fabric_cm/credmgr/swagger_client/models/status200_ok_no_content_data.py
fabric_cm/credmgr/swagger_client/models/status200_ok_paginated.py
fabric_cm/credmgr/swagger_client/models/status200_ok_single.py
fabric_cm/credmgr/swagger_client/models/status400_bad_request.py
fabric_cm/credmgr/swagger_client/models/status400_bad_request_errors.py
fabric_cm/credmgr/swagger_client/models/status401_unauthorized.py
fabric_cm/credmgr/swagger_client/models/status401_unauthorized_errors.py
fabric_cm/credmgr/swagger_client/models/status403_forbidden.py
fabric_cm/credmgr/swagger_client/models/status403_forbidden_errors.py
fabric_cm/credmgr/swagger_client/models/status404_not_found.py
fabric_cm/credmgr/swagger_client/models/status404_not_found_errors.py
fabric_cm/credmgr/swagger_client/models/status500_internal_server_error.py
fabric_cm/credmgr/swagger_client/models/status500_internal_server_error_errors.py
fabric_cm/credmgr/swagger_client/models/token.py
fabric_cm/credmgr/swagger_client/models/token_post.py
fabric_cm/credmgr/swagger_client/models/tokens.py
fabric_cm/credmgr/swagger_client/models/version.py
fabric_credmgr_client-1.6.2.dist-info/LICENSE
fabric_credmgr_client-1.6.2.dist-info/WHEEL
fabric_credmgr_client-1.6.2.dist-info/METADATA
fabric_credmgr_client-1.6.2.dist-info/RECORD
